{
  "template": {
    "type": "JSON",
    "content": [
      {
        "id": "3632710",
        "Flight": "WS2415",
        "Time": "11:15",
        "HotelName": "Royalton Splash Riviera Cancun"
      },
      {
        "id": "3593359",
        "Flight": "WS2471",
        "Time": "06:30",
        "HotelName": "Royalton Splash Riviera Cancun"
      },
      {
        "id": "3593359",
        "Flight": "WS2471",
        "Time": "06:30",
        "HotelName": "Royalton Splash Riviera Cancun"
      },
      {
        "id": "3593338",
        "Flight": "WS2309",
        "Time": "16:10",
        "HotelName": "Royalton Splash Riviera Cancun"
      },
      {
        "id": "4105221",
        "Flight": "AA1192",
        "Time": "16:25",
        "HotelName": "Royalton Splash Riviera Cancun"
      },
      {
        "id": "3572115",
        "Flight": "WS2437",
        "Time": "14:00",
        "HotelName": "Royalton Splash Riviera Cancun"
      },
      {
        "id": "3616398",
        "Flight": "WS2419",
        "Time": "17:00",
        "HotelName": "Royalton Splash Riviera Cancun"
      },
      {
        "id": "3637763",
        "Flight": "WS2471",
        "Time": "06:30",
        "HotelName": "Royalton Splash Riviera Cancun"
      },
      {
        "id": "38092SE466831",
        "Flight": "DL0260",
        "Time": "13:00",
        "HotelName": "Royalton Splash Riviera Cancun"
      },
      {
        "id": "3591560",
        "Flight": "WS2023",
        "Time": "17:25",
        "HotelName": "Royalton Splash Riviera Cancun"
      },
      {
        "id": "3532922",
        "Flight": "WS2437",
        "Time": "14:00",
        "HotelName": "Royalton Splash Riviera Cancun"
      },
      {
        "id": "NY99P2",
        "Flight": "DL0641",
        "Time": "12:40",
        "HotelName": "Royalton Splash Riviera Cancun"
      },
      {
        "id": "3619108",
        "Flight": "WS2415",
        "Time": "11:15",
        "HotelName": "Royalton Splash Riviera Cancun"
      },
      {
        "id": "3644839",
        "Flight": "WS2471",
        "Time": "06:30",
        "HotelName": "Royalton Splash Riviera Cancun"
      },
      {
        "id": "3643056",
        "Flight": "WS2471",
        "Time": "06:30",
        "HotelName": "Royalton Splash Riviera Cancun"
      },
      {
        "id": "3593338",
        "Flight": "WS2309",
        "Time": "16:10",
        "HotelName": "Royalton Splash Riviera Cancun"
      },
      {
        "id": "3591560",
        "Flight": "WS2023",
        "Time": "17:25",
        "HotelName": "Royalton Splash Riviera Cancun"
      }
    ],
    "source": {
      "data_source": "Google Sheets (Private)",
      "update_frequency": "Automated"
    }
  }
}