{
  "templates": {
    "type": "JSON",
    "content": [
      {
        "id": "9890SF696310",
        "Flight": "NOT CONFIRMED",
        "PickupDate": "2025-08-16",
        "PickupTime": "⚠️",
        "HotelName": "CONTACT YOUR ROYALTON EXPERIENCE REP",
        "HotelNumber": 11610
      },
      {
        "id": "4358876",
        "Flight": "B61052",
        "PickupDate": "2025-08-16",
        "PickupTime": "12:25",
        "HotelName": "Royalton CHIC Suites Cancun",
        "HotelNumber": 11610
      },
      {
        "id": "9890SF696311",
        "Flight": "NOT CONFIRMED",
        "PickupDate": "2025-08-16",
        "PickupTime": "⚠️",
        "HotelName": "CONTACT YOUR ROYALTON EXPERIENCE REP",
        "HotelNumber": 11610
      },
      {
        "id": "4296834",
        "Flight": "WN1610",
        "PickupDate": "2025-08-16",
        "PickupTime": "12:45",
        "HotelName": "Royalton CHIC Suites Cancun",
        "HotelNumber": 11610
      },
      {
        "id": "69-7664486",
        "Flight": "Y43502",
        "PickupDate": "2025-08-16",
        "PickupTime": "11:45",
        "HotelName": "Royalton CHIC Suites Cancun",
        "HotelNumber": 11610
      },
      {
        "id": "4358917",
        "Flight": "UA1056",
        "PickupDate": "2025-08-16",
        "PickupTime": "10:13",
        "HotelName": "Royalton CHIC Suites Cancun",
        "HotelNumber": 11610
      },
      {
        "id": "4335764",
        "Flight": "WN306",
        "PickupDate": "2025-08-16",
        "PickupTime": "⚠️",
        "HotelName": "Royalton CHIC Suites Cancun",
        "HotelNumber": 11610
      },
      {
        "id": "4335764",
        "Flight": "WN306",
        "PickupDate": "2025-08-16",
        "PickupTime": "10:20",
        "HotelName": "Royalton CHIC Suites Cancun",
        "HotelNumber": 11610
      },
      {
        "id": "4427598",
        "Flight": "AA1750",
        "PickupDate": "2025-08-16",
        "PickupTime": "11:10",
        "HotelName": "Royalton CHIC Suites Cancun",
        "HotelNumber": 11610
      },
      {
        "id": "9890SF695748",
        "Flight": "DL0618",
        "PickupDate": "2025-08-16",
        "PickupTime": "⚠️",
        "HotelName": "Royalton CHIC Suites Cancun",
        "HotelNumber": 11610
      },
      {
        "id": "9890SF695748",
        "Flight": "DL0618",
        "PickupDate": "2025-08-16",
        "PickupTime": "09:00",
        "HotelName": "Royalton CHIC Suites Cancun",
        "HotelNumber": 11610
      },
      {
        "id": "9890SF676757",
        "Flight": "TBA000",
        "PickupDate": "2025-08-16",
        "PickupTime": "⚠️",
        "HotelName": "Royalton CHIC Suites Cancun",
        "HotelNumber": 11610
      },
      {
        "id": "3683540",
        "Flight": "WS2315",
        "PickupDate": "2025-08-16",
        "PickupTime": "13:25",
        "HotelName": "Royalton CHIC Suites Cancun",
        "HotelNumber": 11610
      },
      {
        "id": "4378166",
        "Flight": "UA1056",
        "PickupDate": "2025-08-16",
        "PickupTime": "10:13",
        "HotelName": "Royalton CHIC Suites Cancun",
        "HotelNumber": 11610
      },
      {
        "id": "144497823",
        "Flight": "WS2963",
        "PickupDate": "2025-08-16",
        "PickupTime": "07:20",
        "HotelName": "Royalton CHIC Suites Cancun",
        "HotelNumber": 11610
      },
      {
        "id": "144055273",
        "Flight": "WS2773",
        "PickupDate": "2025-08-16",
        "PickupTime": "06:00",
        "HotelName": "Royalton CHIC Suites Cancun",
        "HotelNumber": 11610
      },
      {
        "id": "9890SF668995",
        "Flight": "DL618",
        "PickupDate": "2025-08-16",
        "PickupTime": "09:00",
        "HotelName": "Royalton CHIC Suites Cancun",
        "HotelNumber": 11610
      },
      {
        "id": "69-7588586",
        "Flight": "TOM155",
        "PickupDate": "2025-08-16",
        "PickupTime": "14:45",
        "HotelName": "Royalton CHIC Suites Cancun",
        "HotelNumber": 11610
      },
      {
        "id": "4296834",
        "Flight": "WN1616",
        "PickupDate": "2025-08-16",
        "PickupTime": "11:25",
        "HotelName": "Royalton CHIC Suites Cancun",
        "HotelNumber": 11610
      }
    ],
    "source": {
      "data_source": "Google Sheets (Private)",
      "update_frequency": "Automated"
    }
  }
}