{
  "templates": {
    "type": "JSON",
    "content": [
      {
        "id": "3925959",
        "Flight": "NOT CONFIRMED",
        "PickupDate": "2025-08-18",
        "PickupTime": "⚠️",
        "HotelName": "CONTACT YOUR ROYALTON EXPERIENCE REP",
        "HotelNumber": 11610
      },
      {
        "id": "9890SF683607",
        "Flight": "UA1017",
        "PickupDate": "2025-08-18",
        "PickupTime": "09:50",
        "HotelName": "Royalton CHIC Suites Cancun",
        "HotelNumber": 11610
      },
      {
        "id": "9890SF663937",
        "Flight": "WN1996",
        "PickupDate": "2025-08-18",
        "PickupTime": "⚠️",
        "HotelName": "Royalton CHIC Suites Cancun",
        "HotelNumber": 11610
      },
      {
        "id": "9890SF663937",
        "Flight": "WN1996",
        "PickupDate": "2025-08-18",
        "PickupTime": "10:15",
        "HotelName": "Royalton CHIC Suites Cancun",
        "HotelNumber": 11610
      },
      {
        "id": "32ZV13",
        "Flight": "WN308",
        "PickupDate": "2025-08-18",
        "PickupTime": "13:30",
        "HotelName": "Royalton CHIC Suites Cancun",
        "HotelNumber": 11610
      },
      {
        "id": "9890SF627664",
        "Flight": "TBA000",
        "PickupDate": "2025-08-18",
        "PickupTime": "⚠️",
        "HotelName": "Royalton CHIC Suites Cancun",
        "HotelNumber": 11610
      },
      {
        "id": "144054253",
        "Flight": "WS2773",
        "PickupDate": "2025-08-18",
        "PickupTime": "07:45",
        "HotelName": "Royalton CHIC Suites Cancun",
        "HotelNumber": 11610
      },
      {
        "id": "144054253",
        "Flight": "WS2773",
        "PickupDate": "2025-08-18",
        "PickupTime": "07:45",
        "HotelName": "Royalton CHIC Suites Cancun",
        "HotelNumber": 11610
      },
      {
        "id": "9890SF671006",
        "Flight": "NOT CONFIRMED",
        "PickupDate": "2025-08-18",
        "PickupTime": "⚠️",
        "HotelName": "CONTACT YOUR ROYALTON EXPERIENCE REP",
        "HotelNumber": 11610
      },
      {
        "id": "3667473",
        "Flight": "WS2425",
        "PickupDate": "2025-08-18",
        "PickupTime": "09:30",
        "HotelName": "Royalton CHIC Suites Cancun",
        "HotelNumber": 11610
      },
      {
        "id": "9890SF627671",
        "Flight": "NOT CONFIRMED",
        "PickupDate": "2025-08-18",
        "PickupTime": "⚠️",
        "HotelName": "CONTACT YOUR ROYALTON EXPERIENCE REP",
        "HotelNumber": 11610
      },
      {
        "id": "4361830",
        "Flight": "NOT CONFIRMED",
        "PickupDate": "2025-08-18",
        "PickupTime": "⚠️",
        "HotelName": "CONTACT YOUR ROYALTON EXPERIENCE REP",
        "HotelNumber": 11610
      },
      {
        "id": "4277841",
        "Flight": "NOT CONFIRMED",
        "PickupDate": "2025-08-18",
        "PickupTime": "⚠️",
        "HotelName": "CONTACT YOUR ROYALTON EXPERIENCE REP",
        "HotelNumber": 11610
      },
      {
        "id": "9890SF706537",
        "Flight": "AA2588",
        "PickupDate": "2025-08-18",
        "PickupTime": "07:55",
        "HotelName": "Royalton CHIC Suites Cancun",
        "HotelNumber": 11610
      },
      {
        "id": "9890SF697362",
        "Flight": "B61796",
        "PickupDate": "2025-08-18",
        "PickupTime": "09:20",
        "HotelName": "Royalton CHIC Suites Cancun",
        "HotelNumber": 11610
      },
      {
        "id": "9890SF667366",
        "Flight": "UA1948",
        "PickupDate": "2025-08-18",
        "PickupTime": "⚠️",
        "HotelName": "Royalton CHIC Suites Cancun",
        "HotelNumber": 11610
      },
      {
        "id": "9890SF667366",
        "Flight": "UA1948",
        "PickupDate": "2025-08-18",
        "PickupTime": "09:35",
        "HotelName": "Royalton CHIC Suites Cancun",
        "HotelNumber": 11610
      },
      {
        "id": "FNXZ3X",
        "Flight": "F90083",
        "PickupDate": "2025-08-18",
        "PickupTime": "07:00",
        "HotelName": "Royalton CHIC Suites Cancun",
        "HotelNumber": 11610
      },
      {
        "id": "9890SF709692",
        "Flight": "UA1017",
        "PickupDate": "2025-08-18",
        "PickupTime": "10:20",
        "HotelName": "Royalton CHIC Suites Cancun",
        "HotelNumber": 11610
      },
      {
        "id": "9890SF676404",
        "Flight": "AA1068",
        "PickupDate": "2025-08-18",
        "PickupTime": "⚠️",
        "HotelName": "Royalton CHIC Suites Cancun",
        "HotelNumber": 11610
      },
      {
        "id": "9890SF676404",
        "Flight": "AA1068",
        "PickupDate": "2025-08-18",
        "PickupTime": "08:00",
        "HotelName": "Royalton CHIC Suites Cancun",
        "HotelNumber": 11610
      },
      {
        "id": "143411293",
        "Flight": "WS2773",
        "PickupDate": "2025-08-18",
        "PickupTime": "07:45",
        "HotelName": "Royalton CHIC Suites Cancun",
        "HotelNumber": 11610
      },
      {
        "id": "9890SF649118",
        "Flight": "WN1616",
        "PickupDate": "2025-08-18",
        "PickupTime": "⚠️",
        "HotelName": "Royalton CHIC Suites Cancun",
        "HotelNumber": 11610
      },
      {
        "id": "9890SF649118",
        "Flight": "WN1616",
        "PickupDate": "2025-08-18",
        "PickupTime": "09:50",
        "HotelName": "Royalton CHIC Suites Cancun",
        "HotelNumber": 11610
      },
      {
        "id": "4057618",
        "Flight": "AA2665",
        "PickupDate": "2025-08-18",
        "PickupTime": "11:25",
        "HotelName": "Royalton CHIC Suites Cancun",
        "HotelNumber": 11610
      },
      {
        "id": "9890SF710447",
        "Flight": "WN1616",
        "PickupDate": "2025-08-18",
        "PickupTime": "10:20",
        "HotelName": "Royalton CHIC Suites Cancun",
        "HotelNumber": 11610
      },
      {
        "id": "9890SF710447",
        "Flight": "WN1616",
        "PickupDate": "2025-08-18",
        "PickupTime": "14:30",
        "HotelName": "Royalton CHIC Suites Cancun",
        "HotelNumber": 11610
      },
      {
        "id": "9890SF627594",
        "Flight": "AA1192",
        "PickupDate": "2025-08-18",
        "PickupTime": "12:35",
        "HotelName": "Royalton CHIC Suites Cancun",
        "HotelNumber": 11610
      },
      {
        "id": "9890SF664176",
        "Flight": "NK1281",
        "PickupDate": "2025-08-18",
        "PickupTime": "08:00",
        "HotelName": "Royalton CHIC Suites Cancun",
        "HotelNumber": 11610
      },
      {
        "id": "9890SF712387",
        "Flight": "AA1971",
        "PickupDate": "2025-08-18",
        "PickupTime": "07:30",
        "HotelName": "Royalton CHIC Suites Cancun",
        "HotelNumber": 11610
      },
      {
        "id": "9890SF664509",
        "Flight": "TBA000",
        "PickupDate": "2025-08-18",
        "PickupTime": "⚠️",
        "HotelName": "Royalton CHIC Suites Cancun",
        "HotelNumber": 11610
      },
      {
        "id": "9890SF706532",
        "Flight": "AA2588",
        "PickupDate": "2025-08-18",
        "PickupTime": "07:55",
        "HotelName": "Royalton CHIC Suites Cancun",
        "HotelNumber": 11610
      },
      {
        "id": "4374885",
        "Flight": "NOT CONFIRMED",
        "PickupDate": "2025-08-18",
        "PickupTime": "⚠️",
        "HotelName": "CONTACT YOUR ROYALTON EXPERIENCE REP",
        "HotelNumber": 11610
      },
      {
        "id": "4420959",
        "Flight": "B6114",
        "PickupDate": "2025-08-18",
        "PickupTime": "05:45",
        "HotelName": "Royalton CHIC Suites Cancun",
        "HotelNumber": 11610
      },
      {
        "id": "4420959",
        "Flight": "B6114",
        "PickupDate": "2025-08-18",
        "PickupTime": "08:55",
        "HotelName": "Royalton CHIC Suites Cancun",
        "HotelNumber": 11610
      },
      {
        "id": "9890SF651530",
        "Flight": "NOT CONFIRMED",
        "PickupDate": "2025-08-18",
        "PickupTime": "⚠️",
        "HotelName": "CONTACT YOUR ROYALTON EXPERIENCE REP",
        "HotelNumber": 11610
      }
    ],
    "source": {
      "data_source": "Google Sheets (Private)",
      "update_frequency": "Automated"
    }
  }
}