{
  "templates": {
    "type": "JSON",
    "content": [
      {
        "id": "9890SE602068",
        "Flight": "TBA000",
        "PickupDate": "2025-08-07",
        "PickupTime": "⚠️",
        "HotelName": "Royalton CHIC Suites Cancun",
        "HotelNumber": 11610
      },
      {
        "id": "9890SE602068",
        "Flight": "NOT CONFIRMED",
        "PickupDate": "2025-08-07",
        "PickupTime": "⚠️",
        "HotelName": "CONTACT YOUR ROYALTON EXPERIENCE REP",
        "HotelNumber": 11610
      },
      {
        "id": "9890SF659951",
        "Flight": "NOT CONFIRMED",
        "PickupDate": "2025-08-07",
        "PickupTime": "⚠️",
        "HotelName": "CONTACT YOUR ROYALTON EXPERIENCE REP",
        "HotelNumber": 11610
      },
      {
        "id": "9890SF659951",
        "Flight": "NOT CONFIRMED",
        "PickupDate": "2025-08-07",
        "PickupTime": "⚠️",
        "HotelName": "CONTACT YOUR ROYALTON EXPERIENCE REP",
        "HotelNumber": 11610
      },
      {
        "id": "9890SE614052",
        "Flight": "NOT CONFIRMED",
        "PickupDate": "2025-08-07",
        "PickupTime": "⚠️",
        "HotelName": "CONTACT YOUR ROYALTON EXPERIENCE REP",
        "HotelNumber": 11610
      },
      {
        "id": "9890SF661475",
        "Flight": "626",
        "PickupDate": "2025-08-07",
        "PickupTime": "09:10",
        "HotelName": "Royalton CHIC Suites Cancun",
        "HotelNumber": 11610
      },
      {
        "id": "4131776",
        "Flight": "AA792",
        "PickupDate": "2025-08-07",
        "PickupTime": "14:15",
        "HotelName": "Royalton CHIC Suites Cancun",
        "HotelNumber": 11610
      },
      {
        "id": "4132033",
        "Flight": "AA792",
        "PickupDate": "2025-08-07",
        "PickupTime": "14:15",
        "HotelName": "Royalton CHIC Suites Cancun",
        "HotelNumber": 11610
      },
      {
        "id": "144329103",
        "Flight": "WS2315",
        "PickupDate": "2025-08-07",
        "PickupTime": "12:40",
        "HotelName": "Royalton CHIC Suites Cancun",
        "HotelNumber": 11610
      },
      {
        "id": "9890SE591141",
        "Flight": "B61852",
        "PickupDate": "2025-08-07",
        "PickupTime": "02:30",
        "HotelName": "Royalton CHIC Suites Cancun",
        "HotelNumber": 11610
      }
    ],
    "source": {
      "data_source": "Google Sheets (Private)",
      "update_frequency": "Automated"
    }
  }
}