{
  "templates": {
    "type": "JSON",
    "content": [
      {
        "id": "144221943",
        "Flight": "WS2775",
        "PickupDate": "2026-01-15",
        "PickupTime": "09:25",
        "HotelName": "Royalton CHIC Suites Cancun",
        "HotelNumber": 11610
      },
      {
        "id": "148948572",
        "Flight": "WS2817",
        "PickupDate": "2026-01-15",
        "PickupTime": "15:30",
        "HotelName": "Royalton CHIC Suites Cancun",
        "HotelNumber": 11610
      },
      {
        "id": "9890SF769444",
        "Flight": "NOT CONFIRMED",
        "PickupDate": "2026-01-14",
        "PickupTime": "⚠️",
        "HotelName": "CONTACT YOUR ROYALTON EXPERIENCE REP",
        "HotelNumber": 11610
      },
      {
        "id": "148717622",
        "Flight": "WS2965",
        "PickupDate": "2026-01-15",
        "PickupTime": "11:15",
        "HotelName": "Royalton CHIC Suites Cancun",
        "HotelNumber": 11610
      },
      {
        "id": "148003985",
        "Flight": "WS2773",
        "PickupDate": "2026-01-15",
        "PickupTime": "08:30",
        "HotelName": "Royalton CHIC Suites Cancun",
        "HotelNumber": 11610
      },
      {
        "id": "148176463",
        "Flight": "WS2201",
        "PickupDate": "2026-01-15",
        "PickupTime": "13:20",
        "HotelName": "Royalton CHIC Suites Cancun",
        "HotelNumber": 11610
      },
      {
        "id": "148827833",
        "Flight": "WS2965",
        "PickupDate": "2026-01-15",
        "PickupTime": "11:15",
        "HotelName": "Royalton CHIC Suites Cancun",
        "HotelNumber": 11610
      },
      {
        "id": "9890SF651103",
        "Flight": "UA1988",
        "PickupDate": "2026-01-15",
        "PickupTime": "04:30",
        "HotelName": "Royalton CHIC Suites Cancun",
        "HotelNumber": 11610
      },
      {
        "id": "918RM4",
        "Flight": "DL0626",
        "PickupDate": "2026-01-15",
        "PickupTime": "11:45",
        "HotelName": "Royalton CHIC Suites Cancun",
        "HotelNumber": 11610
      },
      {
        "id": "149283273",
        "Flight": "WS2817",
        "PickupDate": "2026-01-15",
        "PickupTime": "15:30",
        "HotelName": "Royalton CHIC Suites Cancun",
        "HotelNumber": 11610
      },
      {
        "id": "148700623",
        "Flight": "WS2965",
        "PickupDate": "2026-01-15",
        "PickupTime": "11:15",
        "HotelName": "Royalton CHIC Suites Cancun",
        "HotelNumber": 11610
      },
      {
        "id": "148828413",
        "Flight": "WS2965",
        "PickupDate": "2026-01-15",
        "PickupTime": "11:15",
        "HotelName": "Royalton CHIC Suites Cancun",
        "HotelNumber": 11610
      },
      {
        "id": "148804223",
        "Flight": "WS2817",
        "PickupDate": "2026-01-15",
        "PickupTime": "15:30",
        "HotelName": "Royalton CHIC Suites Cancun",
        "HotelNumber": 11610
      },
      {
        "id": "148839973",
        "Flight": "WS2135",
        "PickupDate": "2026-01-15",
        "PickupTime": "12:20",
        "HotelName": "Royalton CHIC Suites Cancun",
        "HotelNumber": 11610
      },
      {
        "id": "148118152",
        "Flight": "WS2793",
        "PickupDate": "2026-01-15",
        "PickupTime": "10:35",
        "HotelName": "Royalton CHIC Suites Cancun",
        "HotelNumber": 11610
      },
      {
        "id": "9890SF770390",
        "Flight": "NK1030",
        "PickupDate": "2026-01-15",
        "PickupTime": "07:35",
        "HotelName": "Royalton CHIC Suites Cancun",
        "HotelNumber": 11610
      },
      {
        "id": "4290918",
        "Flight": "B6172",
        "PickupDate": "2026-01-15",
        "PickupTime": "09:55",
        "HotelName": "Royalton CHIC Suites Cancun",
        "HotelNumber": 11610
      },
      {
        "id": "147910293",
        "Flight": "WS2965",
        "PickupDate": "2026-01-15",
        "PickupTime": "11:15",
        "HotelName": "Royalton CHIC Suites Cancun",
        "HotelNumber": 11610
      },
      {
        "id": "147910443",
        "Flight": "WS2965",
        "PickupDate": "2026-01-15",
        "PickupTime": "11:15",
        "HotelName": "Royalton CHIC Suites Cancun",
        "HotelNumber": 11610
      },
      {
        "id": "147675183",
        "Flight": "WS2301",
        "PickupDate": "2026-01-15",
        "PickupTime": "13:55",
        "HotelName": "Royalton CHIC Suites Cancun",
        "HotelNumber": 11610
      },
      {
        "id": "150056343",
        "Flight": "WS2775",
        "PickupDate": "2026-01-15",
        "PickupTime": "09:25",
        "HotelName": "Royalton CHIC Suites Cancun",
        "HotelNumber": 11610
      },
      {
        "id": "149132253",
        "Flight": "WS2129",
        "PickupDate": "2026-01-15",
        "PickupTime": "12:45",
        "HotelName": "Royalton CHIC Suites Cancun",
        "HotelNumber": 11610
      },
      {
        "id": "148176293",
        "Flight": "WS2201",
        "PickupDate": "2026-01-15",
        "PickupTime": "13:20",
        "HotelName": "Royalton CHIC Suites Cancun",
        "HotelNumber": 11610
      },
      {
        "id": "149143853",
        "Flight": "WS2129",
        "PickupDate": "2026-01-15",
        "PickupTime": "12:45",
        "HotelName": "Royalton CHIC Suites Cancun",
        "HotelNumber": 11610
      },
      {
        "id": "148839363",
        "Flight": "WS2817",
        "PickupDate": "2026-01-15",
        "PickupTime": "15:30",
        "HotelName": "Royalton CHIC Suites Cancun",
        "HotelNumber": 11610
      },
      {
        "id": "147648433",
        "Flight": "WS2301",
        "PickupDate": "2026-01-15",
        "PickupTime": "13:55",
        "HotelName": "Royalton CHIC Suites Cancun",
        "HotelNumber": 11610
      }
    ],
    "source": {
      "data_source": "Google Sheets (Private)",
      "update_frequency": "Automated"
    }
  }
}