{
  "templates": {
    "type": "JSON",
    "content": [
      {
        "id": "4134075",
        "Flight": "WN1996",
        "PickupDate": "2025-06-29",
        "PickupTime": "07:15",
        "HotelName": "Royalton CHIC Suites Cancun",
        "HotelNumber": 11610
      },
      {
        "id": "4255385",
        "Flight": "F945",
        "PickupDate": "2025-06-29",
        "PickupTime": "⚠️",
        "HotelName": "Royalton CHIC Suites Cancun",
        "HotelNumber": 11610
      },
      {
        "id": "4255385",
        "Flight": "F945",
        "PickupDate": "2025-06-29",
        "PickupTime": "07:35",
        "HotelName": "Royalton CHIC Suites Cancun",
        "HotelNumber": 11610
      },
      {
        "id": "4243409",
        "Flight": "F983",
        "PickupDate": "2025-06-29",
        "PickupTime": "07:35",
        "HotelName": "Royalton CHIC Suites Cancun",
        "HotelNumber": 11610
      },
      {
        "id": "4243409",
        "Flight": "WN217",
        "PickupDate": "2025-06-29",
        "PickupTime": "05:00",
        "HotelName": "Royalton CHIC Suites Cancun",
        "HotelNumber": 11610
      },
      {
        "id": "4151493",
        "Flight": "UA1667",
        "PickupDate": "2025-06-29",
        "PickupTime": "11:30",
        "HotelName": "Royalton CHIC Suites Cancun",
        "HotelNumber": 11610
      },
      {
        "id": "9890SE564795",
        "Flight": "NOT CONFIRMED",
        "PickupDate": "2025-06-29",
        "PickupTime": "⚠️",
        "HotelName": "CONTACT YOUR ROYALTON EXPERIENCE REP",
        "HotelNumber": 11610
      },
      {
        "id": "9890SE564795",
        "Flight": "NOT CONFIRMED",
        "PickupDate": "2025-06-29",
        "PickupTime": "⚠️",
        "HotelName": "CONTACT YOUR ROYALTON EXPERIENCE REP",
        "HotelNumber": 11610
      },
      {
        "id": "9890SE564798",
        "Flight": "NOT CONFIRMED",
        "PickupDate": "2025-06-29",
        "PickupTime": "⚠️",
        "HotelName": "CONTACT YOUR ROYALTON EXPERIENCE REP",
        "HotelNumber": 11610
      },
      {
        "id": "9890SE564798",
        "Flight": "NOT CONFIRMED",
        "PickupDate": "2025-06-29",
        "PickupTime": "⚠️",
        "HotelName": "CONTACT YOUR ROYALTON EXPERIENCE REP",
        "HotelNumber": 11610
      },
      {
        "id": "9890SF669471",
        "Flight": "NK344",
        "PickupDate": "2025-06-29",
        "PickupTime": "⚠️",
        "HotelName": "Royalton CHIC Suites Cancun",
        "HotelNumber": 11610
      },
      {
        "id": "9890SF669471",
        "Flight": "NK344",
        "PickupDate": "2025-06-29",
        "PickupTime": "10:20",
        "HotelName": "Royalton CHIC Suites Cancun",
        "HotelNumber": 11610
      },
      {
        "id": "9890SF629799",
        "Flight": "B652",
        "PickupDate": "2025-06-29",
        "PickupTime": "14:30",
        "HotelName": "Royalton CHIC Suites Cancun",
        "HotelNumber": 11610
      },
      {
        "id": "4268733",
        "Flight": "SY508",
        "PickupDate": "2025-06-29",
        "PickupTime": "05:45",
        "HotelName": "Royalton CHIC Suites Cancun",
        "HotelNumber": 11610
      },
      {
        "id": "9890SE577406",
        "Flight": "NOT CONFIRMED",
        "PickupDate": "2025-06-29",
        "PickupTime": "⚠️",
        "HotelName": "CONTACT YOUR ROYALTON EXPERIENCE REP",
        "HotelNumber": 11610
      },
      {
        "id": "9890SE577406",
        "Flight": "NOT CONFIRMED",
        "PickupDate": "2025-06-29",
        "PickupTime": "⚠️",
        "HotelName": "CONTACT YOUR ROYALTON EXPERIENCE REP",
        "HotelNumber": 11610
      },
      {
        "id": "9890SF663530",
        "Flight": "DL609",
        "PickupDate": "2025-06-29",
        "PickupTime": "⚠️",
        "HotelName": "Royalton CHIC Suites Cancun",
        "HotelNumber": 11610
      },
      {
        "id": "9890SF663530",
        "Flight": "DL609",
        "PickupDate": "2025-06-29",
        "PickupTime": "04:20",
        "HotelName": "Royalton CHIC Suites Cancun",
        "HotelNumber": 11610
      },
      {
        "id": "9890SE577407",
        "Flight": "NOT CONFIRMED",
        "PickupDate": "2025-06-29",
        "PickupTime": "⚠️",
        "HotelName": "CONTACT YOUR ROYALTON EXPERIENCE REP",
        "HotelNumber": 11610
      },
      {
        "id": "9890SE577407",
        "Flight": "NOT CONFIRMED",
        "PickupDate": "2025-06-29",
        "PickupTime": "⚠️",
        "HotelName": "CONTACT YOUR ROYALTON EXPERIENCE REP",
        "HotelNumber": 11610
      },
      {
        "id": "9890SF671670",
        "Flight": "TBA000",
        "PickupDate": "2025-06-29",
        "PickupTime": "⚠️",
        "HotelName": "Royalton CHIC Suites Cancun",
        "HotelNumber": 11610
      },
      {
        "id": "9890SF635779",
        "Flight": "DL609",
        "PickupDate": "2025-06-29",
        "PickupTime": "04:20",
        "HotelName": "Royalton CHIC Suites Cancun",
        "HotelNumber": 11610
      },
      {
        "id": "9890SF635779",
        "Flight": "NOT CONFIRMED",
        "PickupDate": "2025-06-29",
        "PickupTime": "⚠️",
        "HotelName": "CONTACT YOUR ROYALTON EXPERIENCE REP",
        "HotelNumber": 11610
      },
      {
        "id": "9890SF635779",
        "Flight": "NOT CONFIRMED",
        "PickupDate": "2025-06-29",
        "PickupTime": "⚠️",
        "HotelName": "CONTACT YOUR ROYALTON EXPERIENCE REP",
        "HotelNumber": 11610
      },
      {
        "id": "9890SE599168",
        "Flight": "206",
        "PickupDate": "2025-06-29",
        "PickupTime": "⚠️",
        "HotelName": "Royalton CHIC Suites Cancun",
        "HotelNumber": 11610
      },
      {
        "id": "9890SE599168",
        "Flight": "206",
        "PickupDate": "2025-06-29",
        "PickupTime": "06:30",
        "HotelName": "Royalton CHIC Suites Cancun",
        "HotelNumber": 11610
      },
      {
        "id": "9890SE577405",
        "Flight": "TBA000",
        "PickupDate": "2025-06-29",
        "PickupTime": "⚠️",
        "HotelName": "Royalton CHIC Suites Cancun",
        "HotelNumber": 11610
      },
      {
        "id": "9890SE528456",
        "Flight": "AA2248",
        "PickupDate": "2025-06-29",
        "PickupTime": "07:15",
        "HotelName": "Royalton CHIC Suites Cancun",
        "HotelNumber": 11610
      },
      {
        "id": "4193794",
        "Flight": "NK3643",
        "PickupDate": "2025-06-29",
        "PickupTime": "05:45",
        "HotelName": "Royalton CHIC Suites Cancun",
        "HotelNumber": 11610
      },
      {
        "id": "9890SF669952",
        "Flight": "NK344",
        "PickupDate": "2025-06-29",
        "PickupTime": "⚠️",
        "HotelName": "Royalton CHIC Suites Cancun",
        "HotelNumber": 11610
      },
      {
        "id": "9890SF669952",
        "Flight": "NK344",
        "PickupDate": "2025-06-29",
        "PickupTime": "10:20",
        "HotelName": "Royalton CHIC Suites Cancun",
        "HotelNumber": 11610
      },
      {
        "id": "9890SF635776",
        "Flight": "TBA000",
        "PickupDate": "2025-06-29",
        "PickupTime": "⚠️",
        "HotelName": "Royalton CHIC Suites Cancun",
        "HotelNumber": 11610
      },
      {
        "id": "9890SF649480",
        "Flight": "NOT CONFIRMED",
        "PickupDate": "2025-06-29",
        "PickupTime": "⚠️",
        "HotelName": "CONTACT YOUR ROYALTON EXPERIENCE REP",
        "HotelNumber": 11610
      },
      {
        "id": "9890SF649480",
        "Flight": "NOT CONFIRMED",
        "PickupDate": "2025-06-29",
        "PickupTime": "⚠️",
        "HotelName": "CONTACT YOUR ROYALTON EXPERIENCE REP",
        "HotelNumber": 11610
      },
      {
        "id": "9890SF646052",
        "Flight": "UPP000",
        "PickupDate": "2025-06-29",
        "PickupTime": "⚠️",
        "HotelName": "Royalton CHIC Suites Cancun",
        "HotelNumber": 11610
      },
      {
        "id": "9890SE528453",
        "Flight": "AA2248",
        "PickupDate": "2025-06-29",
        "PickupTime": "07:15",
        "HotelName": "Royalton CHIC Suites Cancun",
        "HotelNumber": 11610
      },
      {
        "id": "9890SF649964",
        "Flight": "HKF5GJ",
        "PickupDate": "2025-06-29",
        "PickupTime": "05:45",
        "HotelName": "Royalton CHIC Suites Cancun",
        "HotelNumber": 11610
      },
      {
        "id": "9890SE609014",
        "Flight": "UA1133",
        "PickupDate": "2025-06-29",
        "PickupTime": "⚠️",
        "HotelName": "Royalton CHIC Suites Cancun",
        "HotelNumber": 11610
      },
      {
        "id": "9890SE609014",
        "Flight": "UA1133",
        "PickupDate": "2025-06-29",
        "PickupTime": "12:40",
        "HotelName": "Royalton CHIC Suites Cancun",
        "HotelNumber": 11610
      },
      {
        "id": "9890SF649484",
        "Flight": "TBA000",
        "PickupDate": "2025-06-29",
        "PickupTime": "⚠️",
        "HotelName": "Royalton CHIC Suites Cancun",
        "HotelNumber": 11610
      },
      {
        "id": "9890SF684949",
        "Flight": "NK344",
        "PickupDate": "2025-06-29",
        "PickupTime": "09:40",
        "HotelName": "Royalton CHIC Suites Cancun",
        "HotelNumber": 11610
      },
      {
        "id": "9890SF668714",
        "Flight": "TBA000",
        "PickupDate": "2025-06-29",
        "PickupTime": "⚠️",
        "HotelName": "Royalton CHIC Suites Cancun",
        "HotelNumber": 11610
      },
      {
        "id": "9890SF668714",
        "Flight": "NOT CONFIRMED",
        "PickupDate": "2025-06-29",
        "PickupTime": "⚠️",
        "HotelName": "CONTACT YOUR ROYALTON EXPERIENCE REP",
        "HotelNumber": 11610
      }
    ],
    "source": {
      "data_source": "Google Sheets (Private)",
      "update_frequency": "Automated"
    }
  }
}